AUTHORS.rst
LICENSE.txt
README.md
setup.cfg
setup.py
tssearch/__init__.py
tssearch.egg-info/PKG-INFO
tssearch.egg-info/SOURCES.txt
tssearch.egg-info/dependency_links.txt
tssearch.egg-info/requires.txt
tssearch.egg-info/top_level.txt
tssearch/distances/__init__.py
tssearch/distances/compute_distance.py
tssearch/distances/distances.json
tssearch/distances/elastic_distances.py
tssearch/distances/elastic_utils.py
tssearch/distances/lockstep_distances.py
tssearch/distances/lockstep_utils.py
tssearch/distances/time_distances.py
tssearch/examples/__init__.py
tssearch/examples/ecg.pickle
tssearch/examples/ecg_example_data.py
tssearch/search/__init__.py
tssearch/search/query_search.py
tssearch/search/search_utils.py
tssearch/search/segmentation.py
tssearch/utils/__init__.py
tssearch/utils/add_personal_distance.py
tssearch/utils/distances_settings.py
tssearch/utils/preprocessing.py
tssearch/utils/visualisation.py