Metadata-Version: 2.1
Name: tssearch
Version: 0.1.3
Summary: Library for time series subsequence search
Home-page: UNKNOWN
Author: Fraunhofer Portugal
License: UNKNOWN
Download-URL: https://github.com/fraunhoferportugal/tssearch/archive/refs/tags/v0.1.3.tar.gz
Platform: UNKNOWN
Classifier: Programming Language :: Python :: 3
Classifier: License :: OSI Approved :: MIT License
Classifier: Operating System :: OS Independent
License-File: LICENSE.txt
License-File: AUTHORS.rst
